trytond/modules/health_profile/__init__.py
trytond/modules/health_profile/tryton.cfg
trytond/modules/health_profile/doc/index.rst
trytond/modules/health_profile/locale/ar.po
trytond/modules/health_profile/locale/de.po
trytond/modules/health_profile/locale/es.po
trytond/modules/health_profile/locale/fr.po
trytond/modules/health_profile/locale/it_IT.po
trytond/modules/health_profile/locale/ja_JP.po
trytond/modules/health_profile/locale/lo.po
trytond/modules/health_profile/locale/zh_CN.po
trytond/modules/health_profile/tests/__init__.py
trytond/modules/health_profile/tests/test_health_profile.py
gnuhealth_profile-4.4.1.dist-info/COPYING
gnuhealth_profile-4.4.1.dist-info/METADATA
gnuhealth_profile-4.4.1.dist-info/WHEEL
gnuhealth_profile-4.4.1.dist-info/entry_points.txt
gnuhealth_profile-4.4.1.dist-info/top_level.txt
gnuhealth_profile-4.4.1.dist-info/RECORD
