Metadata-Version: 2.1
Name: gnuhealth_profile
Version: 4.4.1
Summary: GNU Health profile with common packages
Home-page: https://www.gnuhealth.org
Download-URL: http://ftp.gnu.org/gnu/health/
Author: GNU Solidario
Author-email: health@gnusolidario.org
License: GPL-3
Classifier: Development Status :: 5 - Production/Stable
Classifier: Environment :: Plugins
Classifier: Framework :: Tryton
Classifier: Intended Audience :: Developers
Classifier: Intended Audience :: Healthcare Industry
Classifier: License :: OSI Approved :: GNU General Public License (GPL)
Classifier: Natural Language :: English
Classifier: Natural Language :: Spanish
Classifier: Operating System :: OS Independent
Classifier: Programming Language :: Python :: 3
Classifier: Topic :: Scientific/Engineering :: Bio-Informatics
Classifier: Topic :: Scientific/Engineering :: Medical Science Apps.
License-File: COPYING
Requires-Dist: gnuhealth ==4.4.1
Requires-Dist: gnuhealth-socioeconomics ==4.4.1
Requires-Dist: gnuhealth-lifestyle ==4.4.1
Requires-Dist: gnuhealth-genetics ==4.4.1
Requires-Dist: gnuhealth-icd10 ==4.4.1
Requires-Dist: gnuhealth-gyneco ==4.4.1
Requires-Dist: gnuhealth-pediatrics ==4.4.1
Requires-Dist: gnuhealth-surgery ==4.4.1
Requires-Dist: gnuhealth-lab ==4.4.1
Requires-Dist: gnuhealth-inpatient ==4.4.1
